ratatoskr/__init__.py
ratatoskr/exceptions.py
ratatoskr/internal_logger.py
ratatoskr/operation_registry.py
ratatoskr/protectron.py
ratatoskr/schema.py
ratatoskr/utils.py
ratatoskr/operation_wrappers/__init__.py
ratatoskr/operation_wrappers/aws_lambda.py
ratatoskr/operation_wrappers/base_wrappers.py
ratatoskr-0.1.7.dist-info/LICENSE.txt
ratatoskr-0.1.7.dist-info/METADATA
ratatoskr-0.1.7.dist-info/WHEEL
ratatoskr-0.1.7.dist-info/top_level.txt
ratatoskr-0.1.7.dist-info/RECORD
