Metadata-Version: 2.1
Name: ratatoskr
Version: 0.1.7
Summary: 
Provides-Extra: dev
